{
 "genStamp": "2026-07-17 16:37",
 "checkpointWd": "五",
 "today": "2026-07-17",
 "fetchStatus": "ok",
 "expDate": "2026-08-04",
 "nAds": 12,
 "curYM": "2026-07",
 "quarter": {
  "label": "2026-Q3",
  "start": "2026-07-01",
  "end": "2026-09-30",
  "totalDays": 92,
  "months": [
   "2026-07",
   "2026-08",
   "2026-09"
  ]
 },
 "dayOfQuarter": 17,
 "dayOfMonth": 17,
 "dim": 31,
 "subjects": [
  {
   "key": "read",
   "name": "閱讀",
   "q3Target": 3360,
   "monthTargets": {
    "2026-07": 950,
    "2026-08": 1160,
    "2026-09": 1250
   },
   "q3": {
    "target": 3360,
    "actual": 300,
    "actualBk": 287,
    "prog": 8.9,
    "timeProg": 18.5,
    "proj": 1624,
    "attain": 48.3,
    "gap": 1736,
    "remain": 3060,
    "diff": -9.6,
    "status": "behind"
   },
   "cur": {
    "ym": "2026-07",
    "target": 950,
    "actual": 300,
    "actualBk": 287,
    "prog": 31.6,
    "timeProg": 54.8,
    "proj": 547,
    "attain": 57.6,
    "gap": 403,
    "remain": 650,
    "needPerDay": 46.4,
    "dayRateNow": 17.6,
    "recent7Rate": 20.9,
    "diff": -23.3,
    "status": "behind"
   },
   "months": [
    {
     "ym": "2026-07",
     "target": 950,
     "actual": 300,
     "actualBk": 287,
     "isCur": true,
     "isPast": false,
     "proj": 547,
     "gap": 403,
     "prog": 31.6,
     "timeProg": 54.8,
     "status": "behind"
    },
    {
     "ym": "2026-08",
     "target": 1160,
     "actual": 0,
     "actualBk": 0,
     "isCur": false,
     "isPast": false,
     "proj": 0,
     "gap": 1160,
     "prog": 0,
     "timeProg": 0,
     "status": "na"
    },
    {
     "ym": "2026-09",
     "target": 1250,
     "actual": 0,
     "actualBk": 0,
     "isCur": false,
     "isPast": false,
     "proj": 0,
     "gap": 1250,
     "prog": 0,
     "timeProg": 0,
     "status": "na"
    }
   ],
   "weeks": [
    {
     "start": "2026-06-29",
     "end": "2026-07-05",
     "effFrom": "2026-07-01",
     "effTo": "2026-07-05",
     "isCur": false,
     "line": 238,
     "actual": 57,
     "actualBk": 52,
     "gap": 181,
     "status": "fail"
    },
    {
     "start": "2026-07-06",
     "end": "2026-07-12",
     "effFrom": "2026-07-06",
     "effTo": "2026-07-12",
     "isCur": false,
     "line": 238,
     "actual": 151,
     "actualBk": 142,
     "gap": 87,
     "status": "fail"
    },
    {
     "start": "2026-07-13",
     "end": "2026-07-19",
     "effFrom": "2026-07-13",
     "effTo": "2026-07-17",
     "isCur": true,
     "line": 238,
     "actual": 92,
     "actualBk": 93,
     "gap": 146,
     "status": "current"
    }
   ]
  },
  {
   "key": "en",
   "name": "英語",
   "q3Target": 50,
   "monthTargets": {
    "2026-07": null,
    "2026-08": null,
    "2026-09": null
   },
   "ref": true,
   "q3": {
    "target": 50,
    "actual": 25,
    "actualBk": 18,
    "prog": 50,
    "timeProg": 18.5,
    "proj": 135,
    "attain": 270.6,
    "gap": 0,
    "remain": 25,
    "diff": 31.5,
    "status": "ahead"
   },
   "cur": {
    "ym": "2026-07",
    "target": 0,
    "actual": 25,
    "actualBk": 18,
    "prog": 0,
    "timeProg": 54.8,
    "proj": 46,
    "attain": 0,
    "gap": null,
    "remain": 0,
    "needPerDay": 0,
    "dayRateNow": 1.5,
    "recent7Rate": 2,
    "diff": 0,
    "status": "na"
   },
   "months": [
    {
     "ym": "2026-07",
     "target": null,
     "actual": 25,
     "actualBk": 18,
     "isCur": true,
     "isPast": false,
     "proj": 46,
     "gap": null,
     "prog": null,
     "timeProg": 54.8,
     "status": "na"
    },
    {
     "ym": "2026-08",
     "target": null,
     "actual": 0,
     "actualBk": 0,
     "isCur": false,
     "isPast": false,
     "proj": 0,
     "gap": null,
     "prog": null,
     "timeProg": 0,
     "status": "na"
    },
    {
     "ym": "2026-09",
     "target": null,
     "actual": 0,
     "actualBk": 0,
     "isCur": false,
     "isPast": false,
     "proj": 0,
     "gap": null,
     "prog": null,
     "timeProg": 0,
     "status": "na"
    }
   ],
   "weeks": [
    {
     "start": "2026-06-29",
     "end": "2026-07-05",
     "effFrom": "2026-07-01",
     "effTo": "2026-07-05",
     "isCur": false,
     "line": null,
     "actual": 5,
     "actualBk": 5,
     "gap": null,
     "status": "na"
    },
    {
     "start": "2026-07-06",
     "end": "2026-07-12",
     "effFrom": "2026-07-06",
     "effTo": "2026-07-12",
     "isCur": false,
     "line": null,
     "actual": 14,
     "actualBk": 9,
     "gap": null,
     "status": "na"
    },
    {
     "start": "2026-07-13",
     "end": "2026-07-19",
     "effFrom": "2026-07-13",
     "effTo": "2026-07-17",
     "isCur": true,
     "line": null,
     "actual": 6,
     "actualBk": 4,
     "gap": null,
     "status": "na"
    }
   ]
  }
 ],
 "rows": [
  {
   "id": "120247919419730392",
   "name": "25884 ㄈㄊ正音班（Rose）✅",
   "campaign": "L2+L3 ㄈㄊ正音班（Rose）",
   "bl": "Reading",
   "status": "ACTIVE",
   "paused": false,
   "m": 180,
   "b": 167,
   "spend": 1226,
   "cpl": 6.8,
   "m7": 66,
   "budget": 82,
   "bm": {
    "excellent": 5,
    "acceptable": 8,
    "danger": 12,
    "scale_excellent": 5
   },
   "adviceAction": "KEEP",
   "adviceText": "維持現狀",
   "priority": "P2",
   "suggestedBudget": 82,
   "trendWorse": false,
   "trendBetter": false,
   "declineType": null,
   "tag": "keep",
   "tagTxt": "✅ 維持",
   "color": "#6366f1"
  },
  {
   "id": "120250705597430392",
   "name": "25954 Codex-暑假識字練習（Rose）小百科",
   "campaign": "L2+L3 Codex-暑假識字練習（Rose）小百科",
   "bl": "Reading",
   "status": "ACTIVE",
   "paused": false,
   "m": 60,
   "b": 58,
   "spend": 248,
   "cpl": 4.1,
   "m7": 31,
   "budget": 30,
   "bm": {
    "excellent": 5,
    "acceptable": 8,
    "danger": 12,
    "scale_excellent": 5
   },
   "adviceAction": "SCALE",
   "adviceText": "爆款，建議加預算 20-30%",
   "priority": "P2",
   "suggestedBudget": 38,
   "trendWorse": false,
   "trendBetter": false,
   "declineType": null,
   "tag": "scale",
   "tagTxt": "🔥 加碼",
   "color": "#22c55e"
  },
  {
   "id": "120250075411580392",
   "name": "25922 暑期幼兒英語營（Rose）",
   "campaign": "K2 暑期幼兒英語營（Rose）",
   "bl": "English",
   "status": "ACTIVE",
   "paused": false,
   "m": 24,
   "b": 17,
   "spend": 136,
   "cpl": 5.7,
   "m7": 13,
   "budget": 11,
   "bm": {
    "excellent": 8,
    "acceptable": 13,
    "danger": 18,
    "scale_excellent": 8
   },
   "adviceAction": "SCALE",
   "adviceText": "爆款，建議加預算 20-30%",
   "priority": "P2",
   "suggestedBudget": 14,
   "trendWorse": false,
   "trendBetter": false,
   "declineType": null,
   "tag": "scale",
   "tagTxt": "🔥 加碼",
   "color": "#f59e0b"
  },
  {
   "id": "120250997796650392",
   "name": "25962 Codex-108識字卡拼圖（Rose）",
   "campaign": "L2+L3 Codex-108識字卡拼圖（Rose）",
   "bl": "Reading",
   "status": "ACTIVE",
   "paused": false,
   "m": 24,
   "b": 23,
   "spend": 61,
   "cpl": 2.6,
   "m7": 18,
   "budget": 10,
   "bm": {
    "excellent": 5,
    "acceptable": 8,
    "danger": 12,
    "scale_excellent": 5
   },
   "adviceAction": "SCALE",
   "adviceText": "爆款，建議加預算 20-30%",
   "priority": "P2",
   "suggestedBudget": 12,
   "trendWorse": false,
   "trendBetter": false,
   "declineType": null,
   "tag": "testing",
   "tagTxt": "🧪 測試中",
   "color": "#ef4444"
  },
  {
   "id": "120250997803280392",
   "name": "25968 Codex-108識字卡拼圖（Rose）",
   "campaign": "L2+L3 Codex-108識字卡拼圖（Rose）",
   "bl": "Reading",
   "status": "ACTIVE",
   "paused": false,
   "m": 21,
   "b": 24,
   "spend": 66,
   "cpl": 3.1,
   "m7": 16,
   "budget": 10,
   "bm": {
    "excellent": 5,
    "acceptable": 8,
    "danger": 12,
    "scale_excellent": 5
   },
   "adviceAction": "SCALE",
   "adviceText": "爆款，建議加預算 20-30%",
   "priority": "P2",
   "suggestedBudget": 12,
   "trendWorse": false,
   "trendBetter": false,
   "declineType": null,
   "tag": "testing",
   "tagTxt": "🧪 測試中",
   "color": "#a855f7"
  },
  {
   "id": "120251174246100392",
   "name": "25969 復刻-108識字卡拼圖2（Rose）",
   "campaign": "L2+L3 復刻-108識字卡拼圖2（Rose）",
   "bl": "Reading",
   "status": "ACTIVE",
   "paused": false,
   "m": 9,
   "b": 9,
   "spend": 19,
   "cpl": 2.1,
   "m7": 9,
   "budget": 6,
   "bm": {
    "excellent": 5,
    "acceptable": 8,
    "danger": 12,
    "scale_excellent": 5
   },
   "adviceAction": "SCALE",
   "adviceText": "新品表現優異：CPL $2.15 低於合格線 $8.00，轉換 9。建議加預算 30%。",
   "priority": "P2",
   "suggestedBudget": 8,
   "trendWorse": false,
   "trendBetter": false,
   "declineType": null,
   "tag": "testing",
   "tagTxt": "🧪 測試中",
   "color": "#0ea5e9"
  },
  {
   "id": "120251174253190392",
   "name": "25973 復刻-暑假繪本練習包（Rose）",
   "campaign": "L2+L3  復刻-暑假繪本練習包（Rose）",
   "bl": "Reading",
   "status": "ACTIVE",
   "paused": false,
   "m": 2,
   "b": 1,
   "spend": 17,
   "cpl": 8.7,
   "m7": 2,
   "budget": 5,
   "bm": {
    "excellent": 5,
    "acceptable": 8,
    "danger": 12,
    "scale_excellent": 5
   },
   "adviceAction": "cold_start",
   "adviceText": "新品測試中：已花費 $17.31/$36.00，還有 $18.69 觀察空間",
   "priority": "--",
   "suggestedBudget": 5,
   "trendWorse": false,
   "trendBetter": false,
   "declineType": null,
   "tag": "testing",
   "tagTxt": "🧪 測試中",
   "color": "#14b8a6"
  },
  {
   "id": "120251174295520392",
   "name": "25972 復刻-暑假識字練習（Rose）",
   "campaign": "L2+L3  復刻-暑假識字練習（Rose）",
   "bl": "Reading",
   "status": "CAMPAIGN_PAUSED",
   "paused": true,
   "m": 2,
   "b": 2,
   "spend": 15,
   "cpl": 7.3,
   "m7": 2,
   "budget": 5,
   "bm": {
    "excellent": 5,
    "acceptable": 8,
    "danger": 12,
    "scale_excellent": 5
   },
   "adviceAction": "SCALE",
   "adviceText": "新品表現優異：CPL $7.27 低於合格線 $8.00，轉換 2。建議加預算 30%。",
   "priority": "P2",
   "suggestedBudget": 6,
   "trendWorse": false,
   "trendBetter": false,
   "declineType": null,
   "tag": "paused",
   "tagTxt": "⏸ 已暫停",
   "color": "#ec4899"
  },
  {
   "id": "120251174203910392",
   "name": "25971 復刻-暑假注音先修（Rose）",
   "campaign": "L2+L3  復刻-暑假注音先修（Rose）",
   "bl": "Reading",
   "status": "CAMPAIGN_PAUSED",
   "paused": true,
   "m": 1,
   "b": 2,
   "spend": 17,
   "cpl": 17.1,
   "m7": 1,
   "budget": 5,
   "bm": {
    "excellent": 5,
    "acceptable": 8,
    "danger": 12,
    "scale_excellent": 5
   },
   "adviceAction": "cold_start",
   "adviceText": "新品測試中：已花費 $17.10/$36.00，還有 $18.90 觀察空間",
   "priority": "--",
   "suggestedBudget": 5,
   "trendWorse": false,
   "trendBetter": false,
   "declineType": null,
   "tag": "paused",
   "tagTxt": "⏸ 已暫停",
   "color": "#84cc16"
  },
  {
   "id": "120251174248740392",
   "name": "25970 復刻-108識字卡拼圖2（Rose）",
   "campaign": "L2+L3  復刻-108識字卡拼圖2（Rose）",
   "bl": "Reading",
   "status": "CAMPAIGN_PAUSED",
   "paused": true,
   "m": 1,
   "b": 1,
   "spend": 15,
   "cpl": 15.1,
   "m7": 1,
   "budget": 5,
   "bm": {
    "excellent": 5,
    "acceptable": 8,
    "danger": 12,
    "scale_excellent": 5
   },
   "adviceAction": "cold_start",
   "adviceText": "新品測試中：已花費 $15.06/$36.00，還有 $20.94 觀察空間",
   "priority": "--",
   "suggestedBudget": 5,
   "trendWorse": false,
   "trendBetter": false,
   "declineType": null,
   "tag": "paused",
   "tagTxt": "⏸ 已暫停",
   "color": "#f97316"
  },
  {
   "id": "120251174257120392",
   "name": "25974 復刻-暑期幼兒英語營（Rose）",
   "campaign": "K2復刻-暑期幼兒英語營（Rose）",
   "bl": "English",
   "status": "CAMPAIGN_PAUSED",
   "paused": true,
   "m": 1,
   "b": 1,
   "spend": 19,
   "cpl": 18.7,
   "m7": 1,
   "budget": 5,
   "bm": {
    "excellent": 8,
    "acceptable": 13,
    "danger": 18,
    "scale_excellent": 8
   },
   "adviceAction": "cold_start",
   "adviceText": "新品測試中：已花費 $18.66/$54.00，還有 $35.34 觀察空間",
   "priority": "--",
   "suggestedBudget": 5,
   "trendWorse": false,
   "trendBetter": false,
   "declineType": null,
   "tag": "paused",
   "tagTxt": "⏸ 已暫停",
   "color": "#64748b"
  },
  {
   "id": "120231639051860392",
   "name": "25869 注音尋寶卡",
   "campaign": "L2+L3 注音尋寶卡-Rose",
   "bl": "Reading",
   "status": "ACTIVE",
   "paused": false,
   "m": 0,
   "b": 0,
   "spend": 1,
   "cpl": null,
   "m7": 0,
   "budget": 5,
   "bm": {
    "excellent": 5,
    "acceptable": 8,
    "danger": 12,
    "scale_excellent": 5
   },
   "adviceAction": "cold_start",
   "adviceText": "新品測試中：已花費 $8.52/$36.00，還有 $27.48 觀察空間",
   "priority": "--",
   "suggestedBudget": 5,
   "trendWorse": false,
   "trendBetter": false,
   "declineType": null,
   "tag": "testing",
   "tagTxt": "🧪 測試中",
   "color": "#eab308"
  }
 ],
 "advice": {
  "safe": false,
  "needPerDay": 46.4,
  "addlPerDay": 25.5,
  "winnerDaily": 9.4,
  "adsNeeded": 3,
  "topScale": [
   {
    "id": "120250705597430392",
    "name": "25954 Codex-暑假識字練習（Rose）小百科",
    "campaign": "L2+L3 Codex-暑假識字練習（Rose）小百科",
    "bl": "Reading",
    "status": "ACTIVE",
    "paused": false,
    "m": 60,
    "b": 58,
    "spend": 248,
    "cpl": 4.1,
    "m7": 31,
    "budget": 30,
    "bm": {
     "excellent": 5,
     "acceptable": 8,
     "danger": 12,
     "scale_excellent": 5
    },
    "adviceAction": "SCALE",
    "adviceText": "爆款，建議加預算 20-30%",
    "priority": "P2",
    "suggestedBudget": 38,
    "trendWorse": false,
    "trendBetter": false,
    "declineType": null,
    "tag": "scale",
    "tagTxt": "🔥 加碼",
    "color": "#22c55e"
   },
   {
    "id": "120250075411580392",
    "name": "25922 暑期幼兒英語營（Rose）",
    "campaign": "K2 暑期幼兒英語營（Rose）",
    "bl": "English",
    "status": "ACTIVE",
    "paused": false,
    "m": 24,
    "b": 17,
    "spend": 136,
    "cpl": 5.7,
    "m7": 13,
    "budget": 11,
    "bm": {
     "excellent": 8,
     "acceptable": 13,
     "danger": 18,
     "scale_excellent": 8
    },
    "adviceAction": "SCALE",
    "adviceText": "爆款，建議加預算 20-30%",
    "priority": "P2",
    "suggestedBudget": 14,
    "trendWorse": false,
    "trendBetter": false,
    "declineType": null,
    "tag": "scale",
    "tagTxt": "🔥 加碼",
    "color": "#f59e0b"
   }
  ],
  "iterate": [],
  "bestByCpl": [
   {
    "id": "120251174246100392",
    "name": "25969 復刻-108識字卡拼圖2（Rose）",
    "campaign": "L2+L3 復刻-108識字卡拼圖2（Rose）",
    "bl": "Reading",
    "status": "ACTIVE",
    "paused": false,
    "m": 9,
    "b": 9,
    "spend": 19,
    "cpl": 2.1,
    "m7": 9,
    "budget": 6,
    "bm": {
     "excellent": 5,
     "acceptable": 8,
     "danger": 12,
     "scale_excellent": 5
    },
    "adviceAction": "SCALE",
    "adviceText": "新品表現優異：CPL $2.15 低於合格線 $8.00，轉換 9。建議加預算 30%。",
    "priority": "P2",
    "suggestedBudget": 8,
    "trendWorse": false,
    "trendBetter": false,
    "declineType": null,
    "tag": "testing",
    "tagTxt": "🧪 測試中",
    "color": "#0ea5e9"
   },
   {
    "id": "120250997796650392",
    "name": "25962 Codex-108識字卡拼圖（Rose）",
    "campaign": "L2+L3 Codex-108識字卡拼圖（Rose）",
    "bl": "Reading",
    "status": "ACTIVE",
    "paused": false,
    "m": 24,
    "b": 23,
    "spend": 61,
    "cpl": 2.6,
    "m7": 18,
    "budget": 10,
    "bm": {
     "excellent": 5,
     "acceptable": 8,
     "danger": 12,
     "scale_excellent": 5
    },
    "adviceAction": "SCALE",
    "adviceText": "爆款，建議加預算 20-30%",
    "priority": "P2",
    "suggestedBudget": 12,
    "trendWorse": false,
    "trendBetter": false,
    "declineType": null,
    "tag": "testing",
    "tagTxt": "🧪 測試中",
    "color": "#ef4444"
   },
   {
    "id": "120250997803280392",
    "name": "25968 Codex-108識字卡拼圖（Rose）",
    "campaign": "L2+L3 Codex-108識字卡拼圖（Rose）",
    "bl": "Reading",
    "status": "ACTIVE",
    "paused": false,
    "m": 21,
    "b": 24,
    "spend": 66,
    "cpl": 3.1,
    "m7": 16,
    "budget": 10,
    "bm": {
     "excellent": 5,
     "acceptable": 8,
     "danger": 12,
     "scale_excellent": 5
    },
    "adviceAction": "SCALE",
    "adviceText": "爆款，建議加預算 20-30%",
    "priority": "P2",
    "suggestedBudget": 12,
    "trendWorse": false,
    "trendBetter": false,
    "declineType": null,
    "tag": "testing",
    "tagTxt": "🧪 測試中",
    "color": "#a855f7"
   },
   {
    "id": "120250705597430392",
    "name": "25954 Codex-暑假識字練習（Rose）小百科",
    "campaign": "L2+L3 Codex-暑假識字練習（Rose）小百科",
    "bl": "Reading",
    "status": "ACTIVE",
    "paused": false,
    "m": 60,
    "b": 58,
    "spend": 248,
    "cpl": 4.1,
    "m7": 31,
    "budget": 30,
    "bm": {
     "excellent": 5,
     "acceptable": 8,
     "danger": 12,
     "scale_excellent": 5
    },
    "adviceAction": "SCALE",
    "adviceText": "爆款，建議加預算 20-30%",
    "priority": "P2",
    "suggestedBudget": 38,
    "trendWorse": false,
    "trendBetter": false,
    "declineType": null,
    "tag": "scale",
    "tagTxt": "🔥 加碼",
    "color": "#22c55e"
   }
  ]
 },
 "primary": "m",
 "companyNote": [
  "後端資料庫遷移中：Math APP 註冊數 + Math H5 領課數從 2026-05-26 起異常偏低。Reading / English 領課不受影響。",
  "Damer MCP 與 Lark bitable 已交叉驗證：數字相同（共用後端），切換 Damer 無法解決，等待開發完成遷移。"
 ]
}